spice_rack/__init__.py
spice_rack/_api_helpers/__init__.py
spice_rack/_api_helpers/_uvicorn_startup.py
spice_rack/_bases/__init__.py
spice_rack/_bases/_base_base.py
spice_rack/_bases/_dispatchable.py
spice_rack/_bases/_exception/__init__.py
spice_rack/_bases/_exception/_error_info.py
spice_rack/_bases/_exception/_exception_base.py
spice_rack/_bases/_exception/_exception_exception.py
spice_rack/_bases/_exception/_external_wrapper.py
spice_rack/_bases/_exception/_http.py
spice_rack/_bases/_mixins/__init__.py
spice_rack/_bases/_mixins/_guid_mixin.py
spice_rack/_bases/_mixins/_mixin_base.py
spice_rack/_bases/_mixins/_timestamped.py
spice_rack/_bases/_root.py
spice_rack/_bases/_settings/__init__.py
spice_rack/_bases/_settings/_base.py
spice_rack/_bases/_settings/_sources/__init__.py
spice_rack/_bases/_settings/_sources/_base.py
spice_rack/_bases/_settings/_sources/_dot_env_ext.py
spice_rack/_bases/_settings/_sources/_singleton_source.py
spice_rack/_bases/_special_str.py
spice_rack/_bases/_value_model.py
spice_rack/_common_validators/__init__.py
spice_rack/_common_validators/_mutually_exclusive_fields.py
spice_rack/_frozen_registry/__init__.py
spice_rack/_frozen_registry/_base.py
spice_rack/_frozen_registry/_base_old.py
spice_rack/_frozen_registry/_exceptions/__init__.py
spice_rack/_frozen_registry/_exceptions/_dupe_keys.py
spice_rack/_frozen_registry/_exceptions/_item_ix_invalid.py
spice_rack/_frozen_registry/_exceptions/_key_already_exists.py
spice_rack/_frozen_registry/_exceptions/_missing_key.py
spice_rack/_fs_ops/__init__.py
spice_rack/_fs_ops/_constraints.py
spice_rack/_fs_ops/_exceptions.py
spice_rack/_fs_ops/_file_info.py
spice_rack/_fs_ops/_file_systems/__init__.py
spice_rack/_fs_ops/_file_systems/_base.py
spice_rack/_fs_ops/_file_systems/_fs_inference.py
spice_rack/_fs_ops/_file_systems/_gcs.py
spice_rack/_fs_ops/_file_systems/_local.py
spice_rack/_fs_ops/_file_systems/_sftp.py
spice_rack/_fs_ops/_fs_models/__init__.py
spice_rack/_fs_ops/_fs_models/_base.py
spice_rack-0.15.5.dist-info/METADATA
spice_rack-0.15.5.dist-info/WHEEL
spice_rack-0.15.5.dist-info/RECORD
