Metadata-Version: 2.1
Name: spice_rack
Version: 0.15.5
Summary: group of common things we use across different python packages
License: Apache-2.0
Author: Tim Robin
Author-email: timo.a.robin@gmail.com
Requires-Python: >=3.9,<=3.12
Classifier: License :: OSI Approved :: Apache Software License
Classifier: Programming Language :: Python :: 3
Classifier: Programming Language :: Python :: 3.9
Classifier: Programming Language :: Python :: 3.10
Classifier: Programming Language :: Python :: 3.11
Classifier: Programming Language :: Python :: 3.12
Provides-Extra: all
Requires-Dist: dateparser
Requires-Dist: devtools[pygments]
Requires-Dist: flatten-dict
Requires-Dist: fsspec
Requires-Dist: gcsfs (==2024.2.0)
Requires-Dist: inflection
Requires-Dist: jmespath
Requires-Dist: loguru
Requires-Dist: paramiko
Requires-Dist: polars
Requires-Dist: pydantic (>=2,<3)
Requires-Dist: pydantic_settings
Requires-Dist: s3fs
Requires-Dist: stackprinter
Requires-Dist: tabulate
Requires-Dist: typing-inspect
Requires-Dist: urllib3 (<2)
Requires-Dist: uvicorn
